codemaker/__init__.py
codemaker/makecode.py
codemaker/clitools/__init__.py
codemaker/clitools/cli.py
codemaker-0.0.2.2.dist-info/LICENSE
codemaker-0.0.2.2.dist-info/METADATA
codemaker-0.0.2.2.dist-info/WHEEL
codemaker-0.0.2.2.dist-info/entry_points.txt
codemaker-0.0.2.2.dist-info/top_level.txt
codemaker-0.0.2.2.dist-info/RECORD
