Metadata-Version: 2.1
Name: codemaker
Version: 0.0.2.2
Summary: Utils to easily generate code, speed up your workflow.
Home-page: https://gitee.com/peiiii/codemaker
Author: Wang Pei
Author-email: 1535376447@qq.com
License: UNKNOWN
Platform: UNKNOWN
Classifier: Programming Language :: Python :: 3
Classifier: License :: OSI Approved :: MIT License
Classifier: Operating System :: OS Independent
Requires-Python: >=3.0
Requires-Dist: jinja2
Requires-Dist: pyyaml
Requires-Dist: fire
